dreamai_dl/__init__.py
dreamai_dl/_modidx.py
dreamai_dl/core.py
dreamai_dl/data.py
dreamai_dl/imports.py
dreamai_dl/utils.py
dreamai_dl-0.0.13.dist-info/LICENSE
dreamai_dl-0.0.13.dist-info/METADATA
dreamai_dl-0.0.13.dist-info/WHEEL
dreamai_dl-0.0.13.dist-info/entry_points.txt
dreamai_dl-0.0.13.dist-info/top_level.txt
dreamai_dl-0.0.13.dist-info/RECORD
