Metadata-Version: 2.1
Name: dreamai-dl
Version: 0.0.13
Summary: Deep Learning tools based on dreamai.
Home-page: https://github.com/HamzaFarhan/dreamai_dl
Author: HamzaFarhan
Author-email: thehamza96@gmail.com
License: Apache Software License 2.0
Keywords: nbdev jupyter notebook python
Classifier: Development Status :: 4 - Beta
Classifier: Intended Audience :: Developers
Classifier: Natural Language :: English
Classifier: Programming Language :: Python :: 3.7
Classifier: Programming Language :: Python :: 3.8
Classifier: Programming Language :: Python :: 3.9
Classifier: Programming Language :: Python :: 3.10
Classifier: License :: OSI Approved :: Apache Software License
Requires-Python: >=3.7
License-File: LICENSE
Requires-Dist: dreamai
Requires-Dist: fastai
Requires-Dist: lightning
Requires-Dist: scikit-learn
Requires-Dist: setuptools
Requires-Dist: timm
Requires-Dist: torch
Requires-Dist: torchmetrics
Requires-Dist: torchvision
Requires-Dist: pyarrow
Requires-Dist: fastparquet
Provides-Extra: dev
